ruff_lsp/__init__.py
ruff_lsp/__main__.py
ruff_lsp/py.typed
ruff_lsp/server.py
ruff_lsp/settings.py
ruff_lsp/utils.py
ruff_lsp-0.0.61.dist-info/METADATA
ruff_lsp-0.0.61.dist-info/WHEEL
ruff_lsp-0.0.61.dist-info/entry_points.txt
ruff_lsp-0.0.61.dist-info/licenses/LICENSE
ruff_lsp-0.0.61.dist-info/RECORD
